Metadata-Version: 2.4
Name: quapp-pyquil
Version: 0.0.3
Summary: QApp pyquil library supporting QApp Platform for Quantum Computing
Author-email: "CITYNOW Co. Ltd. " <corp@citynow.vn>
License: The MIT License (MIT)
Project-URL: Homepage, https://citynow.asia/
Keywords: quapp,qapp-pyquil,quantum
Classifier: License :: OSI Approved :: MIT License
Classifier: Programming Language :: Python
Classifier: Programming Language :: Python :: 3
Requires-Python: <3.11,>=3.9
License-File: LICENSE
Requires-Dist: quapp-common==0.0.11.dev3
Requires-Dist: pyquil==4.15.0
Provides-Extra: dev
Requires-Dist: black; extra == "dev"
Requires-Dist: bumpver; extra == "dev"
Requires-Dist: isort; extra == "dev"
Requires-Dist: pip-tools; extra == "dev"
Requires-Dist: pytest; extra == "dev"
Dynamic: license-file
